{
  "name": "Yonim",
  "description": "...",
  "area": "North",
  "sectors": [
    {
      "name": "Hamsa",
      "routes": [
        {
          "name": "Pokemon",
          "grade": "5a",
          "type": "Sport",
          "setBy": "Max Shuster, 2005",
          "height": "15",
          "stars": 2
        },
        {
          "name": "Return of the Yokonuba",
          "grade": "5+",
          "type": "Sport",
          "setBy": "Felix Shlomovich & Elad Omer, 2002",
          "height": "14",
          "stars": 1
        },
        {
          "name": "Over The Rainbow Spectacular yet pumpy start through the roof and \"over the rainbow\", followed by some technical moves on the face of the other side.",
          "grade": "6c+",
          "type": "Sport",
          "setBy": "Shimon Bari, 2002",
          "height": "13",
          "stars": 3
        },
        {
          "name": "Hamsa",
          "grade": "5",
          "type": "Sport",
          "setBy": "Felix Shlomovich, 2002",
          "height": "15",
          "stars": 2
        }
      ]
    },
    {
      "name": "Dome",
      "routes": [
        {
          "name": "Pendulum Some sub-optimal bolt placing, but worth the climb and great exposure.   FA: Ofer Blutrich",
          "grade": "6b+",
          "type": "Sport",
          "setBy": "Shimon Bari, 2002",
          "height": "16",
          "stars": 2
        },
        {
          "name": "O.B.'s Traverse  FA: Ofer Blutrich",
          "grade": "7b",
          "type": "Sport",
          "setBy": "Ofer Blutrich, 2002",
          "height": "17",
          "stars": 2
        },
        {
          "name": "TBD",
          "type": "SportProject",
          "setBy": "Max Shuster & Boris Ginzburg, 2005",
          "height": "9"
        },
        {
          "name": "Gold Finger",
          "grade": "7b+",
          "type": "Sport",
          "setBy": "Felix Shlomovich & Ofer Blutrich, 2002",
          "height": "10",
          "stars": 1
        },
        {
          "name": "Gold Finger Extension  FA: Ofer Blutrich",
          "grade": "7c+",
          "type": "Sport",
          "setBy": "Ofer Blutrich & Daniel Katorza, 2008",
          "height": "18",
          "stars": 2
        },
        {
          "name": "Beasty Traverse Spectacular link-up. Start with \"Beasty\", traverse to the right after the 5th bolt. clipping one bolt on \"Gold Finger Extension\", and keep going left into the crux of \"O.B.'s Traverse\" (finishing in it's anchor). No need to clip the first fixed draw on O.B.'s Traverse   FFA: Amir Gilad, 29 Dec 2017  FA: Yona Tan, 29 Dec 2017",
          "grade": "7b",
          "type": "Sport",
          "bolts": " 7",
          "stars": 3
        },
        {
          "name": "Beasty",
          "grade": "7b",
          "type": "Sport",
          "setBy": "Felix Shlomovich, 2003",
          "height": "17",
          "stars": 3
        },
        {
          "name": "Beauty Great line on awesome jugs. One of the best at this grade in the country.",
          "grade": "6a+",
          "type": "Sport",
          "setBy": "Shimon Bari, 2002",
          "height": "17",
          "stars": 3
        },
        {
          "name": "Alabasha",
          "grade": "6a+",
          "type": "Sport",
          "setBy": "Max Shuster, 2003",
          "height": "15",
          "stars": 1
        },
        {
          "name": "The Red Swarm",
          "grade": "7a",
          "type": "Sport",
          "setBy": "Slava Rubin & Boris Ginzburg, 2008",
          "height": "15",
          "stars": 2
        },
        {
          "name": "Lam-Lam",
          "grade": "6a",
          "type": "Sport",
          "setBy": "Felix Shlomovich, 2002",
          "height": "13"
        },
        {
          "name": "Sukaretka",
          "grade": "6b",
          "type": "Sport",
          "setBy": "Felix Shlomovich, 2003",
          "height": "15",
          "stars": 2
        }
      ]
    },
    {
      "name": "Central",
      "routes": [
        {
          "name": "It's O.K.?",
          "grade": "7a+",
          "type": "Sport",
          "setBy": "Max Shuster, 2003",
          "height": "15",
          "stars": 2
        },
        {
          "name": "Go!",
          "grade": "6c",
          "type": "Sport",
          "setBy": "Felix Shlomovich, 2003",
          "height": "14",
          "stars": 2
        },
        {
          "name": "Take Five",
          "grade": "5c+",
          "type": "Sport",
          "setBy": "Slava Rubin & Boris Ginzburg, 2008",
          "height": "15",
          "stars": 3
        },
        {
          "name": "Balagan",
          "grade": "7a",
          "type": "Sport",
          "setBy": "Max Shuster, 2003",
          "height": "14",
          "stars": 2
        },
        {
          "name": "Balance",
          "grade": "6b",
          "type": "Sport",
          "setBy": "Max Shuster, 2003",
          "height": "17",
          "stars": 2
        },
        {
          "name": "Finger Crack",
          "grade": "7a",
          "type": "Sport",
          "setBy": "Slava Rubin & Boris Ginzburg, 2008",
          "height": "10",
          "stars": 1
        },
        {
          "name": "Kozachok",
          "grade": "6b",
          "type": "Sport",
          "setBy": "Slava Rubin, 2010",
          "height": "12",
          "stars": 2
        },
        {
          "name": "Dr. Pita",
          "grade": "6a+",
          "type": "Sport",
          "setBy": "Felix Shlomovich, 2003",
          "height": "13",
          "stars": 2
        }
      ]
    },
    {
      "name": "The Cave",
      "routes": [
        {
          "name": "White Scorpion  FA: Max Shuster",
          "grade": "7a+",
          "type": "Sport",
          "setBy": "Max Shuster, 2008",
          "height": "11",
          "stars": 2
        },
        {
          "name": "The Best Of 80's",
          "grade": "7b+",
          "type": "Sport",
          "setBy": "Max Shuster, 2008",
          "height": "17",
          "stars": 2
        },
        {
          "name": "Katana  FA: Ofer Blutrich",
          "grade": "8a+",
          "type": "Sport",
          "setBy": "Max Shuster, 2012",
          "height": "15",
          "stars": 2
        },
        {
          "name": "Spina Bafida  FA: Ofer Blutrich",
          "grade": "8b+",
          "type": "Sport",
          "setBy": "Ofer Blutrich, 2009",
          "height": "22",
          "stars": 3
        },
        {
          "name": "Billie Jean  FA: Oleg Margulis",
          "grade": "7c",
          "type": "Sport",
          "setBy": "Max Shuster, 2008",
          "height": "15",
          "stars": 2
        },
        {
          "name": "Love & Cough  FA: Oleg Margulis",
          "grade": "7a+",
          "type": "Sport",
          "setBy": "Max Shuster, 2008",
          "height": "12",
          "stars": 2
        },
        {
          "name": "Shakhtar  FA: Slava Rubin",
          "grade": "7a+",
          "type": "Sport",
          "setBy": "Max Shuster, 2012",
          "height": "13",
          "stars": 1
        },
        {
          "name": "Kakashkin Blues  FA: Iftah Kushnir",
          "grade": "7c",
          "type": "Sport",
          "setBy": "Max Shuster, 2005",
          "height": "13",
          "stars": 2
        },
        {
          "name": "Samurai  FA: Ofer Blutrich",
          "grade": "7b",
          "type": "Sport",
          "setBy": "Max Shuster, 2005",
          "height": "16",
          "stars": 3
        },
        {
          "name": "Shogun  FA: Ofer Blutrich",
          "grade": "7c+",
          "type": "Sport",
          "setBy": "Slava Rubin, 2012",
          "height": "17",
          "stars": 2
        },
        {
          "name": "Bruce Lee  FA: Ofer Blutrich",
          "grade": "8a+",
          "type": "Sport",
          "setBy": "Oren Nogradi, 2010",
          "height": "18",
          "stars": 2
        },
        {
          "name": "Hara-Kiri",
          "grade": "7a+",
          "type": "Sport",
          "setBy": "Felix Shlomovich & Max Shuster, 2003",
          "height": "13",
          "stars": 1
        },
        {
          "name": "Wakizashi  FA: Slava Rubin",
          "grade": "6c+",
          "type": "Sport",
          "setBy": "Max Shuster, 2012",
          "height": "11",
          "stars": 2
        },
        {
          "name": "Black Honey  FA: Oleg Margulis",
          "grade": "7a+",
          "type": "Sport",
          "setBy": "Max Shuster, 2010",
          "height": "12",
          "stars": 2
        },
        {
          "name": "Night & Day  FA: Ofer Blutrich",
          "grade": "7b+",
          "type": "Sport",
          "setBy": "Ofer Blutrich, 2009",
          "height": "12",
          "stars": 2
        }
      ]
    },
    {
      "name": "Herman",
      "routes": [
        {
          "name": "The Cut",
          "grade": "5c",
          "type": "Sport",
          "setBy": "Ofer Blutrich, 2002",
          "height": "12",
          "stars": 2
        },
        {
          "name": "Herman",
          "grade": "6c",
          "type": "Sport",
          "setBy": "Felix Shlomovich, 2003",
          "height": "15",
          "stars": 3
        },
        {
          "name": "Blade",
          "grade": "6b+",
          "type": "Sport",
          "setBy": "Felix Shlomovich, 2003",
          "height": "15",
          "stars": 1
        },
        {
          "name": "Rock Gym",
          "grade": "6b",
          "type": "Sport",
          "setBy": "Felix Shlomovich, 2003",
          "height": "11",
          "stars": 1
        },
        {
          "name": "Shaved",
          "grade": "7a",
          "type": "Sport",
          "setBy": "Felix Shlomovich, 2003",
          "height": "12",
          "stars": 3
        },
        {
          "name": "Katorza's Nest",
          "grade": "6c",
          "type": "Sport",
          "setBy": "Felix Shlomovich, 2003",
          "height": "15",
          "stars": 2
        },
        {
          "name": "The Judge",
          "grade": "6b+",
          "type": "Sport",
          "setBy": "Felix Shlomovich, 2002",
          "height": "9",
          "stars": 2
        },
        {
          "name": "Jerry",
          "grade": "6c+",
          "type": "Sport",
          "setBy": "Felix Shlomovich & Max Shuster, 2003",
          "height": "8",
          "stars": 2
        },
        {
          "name": "Tom",
          "grade": "6a+",
          "type": "Sport",
          "setBy": "Felix Shlomovich & Max Shuster, 2003",
          "height": "8",
          "stars": 1
        }
      ]
    }
  ]
}